pmc_downloader/__init__.py
pmc_downloader/pmc_downloader.py
pmc_downloader-0.1.0.dist-info/METADATA
pmc_downloader-0.1.0.dist-info/WHEEL
pmc_downloader-0.1.0.dist-info/top_level.txt
pmc_downloader-0.1.0.dist-info/RECORD
