Metadata-Version: 2.4
Name: pmc_downloader
Version: 0.1.0
Summary: PubMed Central (PMC) Open Access Articles Downloader
License: MIT
Keywords: pubmed pmc literature scientific-articles bioinformatics
Classifier: Development Status :: 4 - Beta
Classifier: Intended Audience :: Science/Research
Classifier: License :: OSI Approved :: MIT License
Classifier: Programming Language :: Python :: 3
Classifier: Operating System :: OS Independent
Classifier: Topic :: Scientific/Engineering :: Bio-Informatics
Requires-Python: >=3.8
Requires-Dist: requests>=2.31.0
Requires-Dist: biopython>=1.81
Dynamic: classifier
Dynamic: description
Dynamic: description-content-type
Dynamic: keywords
Dynamic: license
Dynamic: requires-dist
Dynamic: requires-python
Dynamic: summary
